stagpy/__init__.py
stagpy/__main__.py
stagpy/_helpers.py
stagpy/args.py
stagpy/commands.py
stagpy/config.py
stagpy/datatypes.py
stagpy/dimensions.py
stagpy/error.py
stagpy/field.py
stagpy/parfile.py
stagpy/phyvars.py
stagpy/plates.py
stagpy/processing.py
stagpy/py.typed
stagpy/refstate.py
stagpy/rprof.py
stagpy/stagyydata.py
stagpy/stagyyparsers.py
stagpy/step.py
stagpy/time_series.py
stagpy/xdmf.py
stagpy/_styles/stagpy-paper.mplstyle
stagpy/_styles/stagpy-slides.mplstyle
stagpy-0.20.1.dist-info/LICENSE
stagpy-0.20.1.dist-info/METADATA
stagpy-0.20.1.dist-info/WHEEL
stagpy-0.20.1.dist-info/entry_points.txt
stagpy-0.20.1.dist-info/top_level.txt
stagpy-0.20.1.dist-info/RECORD
