Metadata-Version: 2.1
Name: stagpy
Version: 0.20.1
Summary: Tool for StagYY output files processing
Author: Martina Ulvrova, Stéphane Labrosse
Author-email: Adrien Morison <adrien.morison@gmail.com>
Maintainer-email: Adrien Morison <adrien.morison@gmail.com>
License: Copyright 2015 - present StagPy developers
Project-URL: homepage, https://github.com/StagPython/StagPy
Classifier: Development Status :: 3 - Alpha
Classifier: Intended Audience :: Science/Research
Classifier: License :: OSI Approved :: Apache Software License
Classifier: Programming Language :: Python :: 3 :: Only
Classifier: Programming Language :: Python :: 3.9
Classifier: Programming Language :: Python :: 3.10
Classifier: Programming Language :: Python :: 3.11
Classifier: Programming Language :: Python :: 3.12
Requires-Python: >=3.9
License-File: LICENSE
Requires-Dist: loam ~=0.8.0
Requires-Dist: f90nml >=1.4.4
Requires-Dist: numpy ~=2.0
Requires-Dist: scipy ~=1.13
Requires-Dist: pandas ~=2.2
Requires-Dist: h5py ~=3.11
Requires-Dist: matplotlib ~=3.9
